web_helper/__init__.py
web_helper-0.1.7.dist-info/METADATA
web_helper-0.1.7.dist-info/WHEEL
web_helper-0.1.7.dist-info/top_level.txt
web_helper-0.1.7.dist-info/RECORD
