Metadata-Version: 2.1
Name: web-helper
Version: 0.1.7
Summary: 又一个爬虫新轮子～
Home-page: https://github.com/imfht/RequestsHelper
Author: jinxu
Author-email: fiht@qq.com
License: MIT
Platform: UNKNOWN
Classifier: License :: OSI Approved :: MIT License
Classifier: Programming Language :: Python
Classifier: Programming Language :: Python :: 3
Classifier: Programming Language :: Python :: 3.6
Classifier: Programming Language :: Python :: Implementation :: CPython
Classifier: Programming Language :: Python :: Implementation :: PyPy
Requires-Python: >=3.6.0
Requires-Dist: requests
Requires-Dist: feedparser
Requires-Dist: loguru
Requires-Dist: bs4
